README.rst
setup.cfg
setup.py
pyteos_nc/__init__.py
pyteos_nc/create_interpolants.py
pyteos_nc/netcdf_interface.py
pyteos_nc.egg-info/PKG-INFO
pyteos_nc.egg-info/SOURCES.txt
pyteos_nc.egg-info/dependency_links.txt
pyteos_nc.egg-info/entry_points.txt
pyteos_nc.egg-info/not-zip-safe
pyteos_nc.egg-info/requires.txt
pyteos_nc.egg-info/top_level.txt
pyteos_nc/generators/__init__.py
pyteos_nc/generators/pottemps.py