Metadata-Version: 1.1
Name: pyteos-nc
Version: 0.4
Summary: This package provides command line tools to complement pyteos_air.
Home-page: UNKNOWN
Author: F. Laliberte
Author-email: laliberte.frederic@utoronto.ca
License: BSD
Keywords: thermodynamics atmosphere climate
Platform: UNKNOWN
Classifier: Development Status :: 4 - Beta
Classifier: Intended Audience :: Science/Research
Classifier: Natural Language :: English
Classifier: License :: OSI Approved :: BSD License
Classifier: Programming Language :: Python :: 2.7
Classifier: Programming Language :: Python :: 3.4
Classifier: Programming Language :: Python :: 3.5
Classifier: Programming Language :: Python :: 3.6
Classifier: Topic :: Scientific/Engineering :: Atmospheric Science
Classifier: Topic :: Scientific/Engineering :: Mathematics
